langanisa/__init__.py
langanisa/langanisa.py
langanisa-0.0.1.dist-info/LICENSE
langanisa-0.0.1.dist-info/METADATA
langanisa-0.0.1.dist-info/WHEEL
langanisa-0.0.1.dist-info/top_level.txt
langanisa-0.0.1.dist-info/RECORD
